termprop
