Metadata-Version: 1.0
Name: termprop
Version: 0.1.1
Summary: detects some terminal glitches and advanced facilities information
Home-page: https://github.com/saitoha/termprop
Author: Hayaki Saito (user@zuse.jp)
Author-email: user@zuse.jp
License: MIT
Keywords: terminal
Platform: UNKNOWN
Classifier: Development Status :: 4 - Beta
Classifier: Topic :: Terminals
Classifier: Environment :: Console
Classifier: Intended Audience :: Developers
Classifier: License :: OSI Approved :: MIT License
Classifier: Programming Language :: Python
